pyconn0/__init__.py
pyconn0/api.py
pyconn0/client/__init__.py
pyconn0/client/db/__init__.py
pyconn0/client/db/base.py
pyconn0/client/db/bigquery.py
pyconn0/client/db/mysql.py
pyconn0/client/db/postgresql.py
pyconn0/client/db/sqlite.py
pyconn0/client/lake/__init__.py
pyconn0/client/lake/base.py
pyconn0/client/lake/gcs.py
pyconn0/client/lake/s3.py
pyconn0/enum/__init__.py
pyconn0/enum/db_layer.py
pyconn0/errors/__init__.py
pyconn0/errors/base.py
pyconn0/errors/params.py
pyconn0/model/__init__.py
pyconn0/model/meta_data.py
pyconn0/model/native.py
pyconn0/ops/__init__.py
pyconn0/ops/io/__init__.py
pyconn0/ops/io/export.py
pyconn0/ops/sync/__init__.py
pyconn0/ops/sync/base.py
pyconn0/ops/sync/full.py
pyconn0/ops/sync/general.py
pyconn0/ops/sync/upsert.py
pyconn0/utils/__init__.py
pyconn0/utils/db_utils.py
pyconn0/utils/misc.py
pyconn0/utils/validator.py
pyconn0-0.1.0.dist-info/LICENSE
pyconn0-0.1.0.dist-info/WHEEL
pyconn0-0.1.0.dist-info/METADATA
pyconn0-0.1.0.dist-info/RECORD
