Metadata-Version: 2.1
Name: pyconn0
Version: 0.1.0
Summary: python database manipulation with advanced features
Author: Thompson
Author-email: 51963680+thompson0012@users.noreply.github.com
Requires-Python: >=3.10,<3.11
Classifier: Programming Language :: Python :: 3
Classifier: Programming Language :: Python :: 3.10
Requires-Dist: Humre (>=0.2.0,<0.3.0)
Requires-Dist: addict (>=2.4.0,<3.0.0)
Requires-Dist: bson (>=0.5.10,<0.6.0)
Requires-Dist: orjson (>=3.8.0,<4.0.0)
Requires-Dist: pampy (>=0.3.0,<0.4.0)
Requires-Dist: pendulum (>=2.1.2,<3.0.0)
Requires-Dist: psycopg[binary] (>=3.1.2,<4.0.0)
Requires-Dist: pydantic (>=1.10.1,<2.0.0)
Requires-Dist: sqlglot (>=5.3.1,<6.0.0)
Requires-Dist: sqlmodel (>=0.0.8,<0.0.9)
Requires-Dist: toml (>=0.10.2,<0.11.0)
